metapipeline/__init__.py
metapipeline/base.py
metapipeline-0.1.0.dist-info/WHEEL
metapipeline-0.1.0.dist-info/METADATA
metapipeline-0.1.0.dist-info/RECORD
